setup.py
os_facio_hooks/__init__.py
os_facio_hooks/secrets.py
os_facio_hooks.egg-info/PKG-INFO
os_facio_hooks.egg-info/SOURCES.txt
os_facio_hooks.egg-info/dependency_links.txt
os_facio_hooks.egg-info/not-zip-safe
os_facio_hooks.egg-info/top_level.txt