Metadata-Version: 1.0
Name: os-facio-hooks
Version: 0.1.2
Summary: custom hooks for facio product generation
Home-page: https://github.com/OnShift/microservice-skeleton
Author: Ilya Gotfryd
Author-email: igotfryd@onshift.com
License: N/A
Platform: UNKNOWN
